botrun_pdf_to_text.py
botrun_pdf_to_text-1.1.1.dist-info/METADATA
botrun_pdf_to_text-1.1.1.dist-info/WHEEL
botrun_pdf_to_text-1.1.1.dist-info/entry_points.txt
botrun_pdf_to_text-1.1.1.dist-info/top_level.txt
botrun_pdf_to_text-1.1.1.dist-info/RECORD
