Metadata-Version: 2.1
Name: botrun-pdf-to-text
Version: 1.1.1
Requires-Dist: pypdf ==3.15.0
